TextRegex/regex.py
TxtRegex/regex.py
TxtRegex-1.0.8.dist-info/METADATA
TxtRegex-1.0.8.dist-info/WHEEL
TxtRegex-1.0.8.dist-info/top_level.txt
TxtRegex-1.0.8.dist-info/RECORD
