Metadata-Version: 2.1
Name: TxtRegex
Version: 1.0.8
Summary: Text Regular expression
Home-page: https://github.com/HaloKim/TxtRegex
Author: Halo Kim
Author-email: dev7halo@gmail.com
License: UNKNOWN
Platform: UNKNOWN
Requires-Python: >=3
